kickredis/__init__.py
kickredis/client.py
kickredis/config.py
kickredis/granite/granite_analytics.py
kickredis/granite/kicker_pb2.py
kickredis/granite/kicker_pb2_grpc.py
kickredis/grpc_poc.py
kickredis/mock_analytics.py
kickredis/registry.py
kickredis/server.py
kickredis/services.py
kickredis-0.3.0.dist-info/WHEEL
kickredis-0.3.0.dist-info/METADATA
kickredis-0.3.0.dist-info/RECORD
