Metadata-Version: 2.1
Name: kickredis
Version: 0.3.0
Summary: Kicker client library for redis
Author: Alexi Polenur
Author-email: alexi@polenur.com
Requires-Python: >=3.7,<4.0
Classifier: Programming Language :: Python :: 3
Classifier: Programming Language :: Python :: 3.7
Classifier: Programming Language :: Python :: 3.8
Classifier: Programming Language :: Python :: 3.9
Requires-Dist: grpcio (>=1.35.0,<2.0.0)
Requires-Dist: lightbus (>=1.0.1,<2.0.0)
Requires-Dist: protobuf (>=3.14.0,<4.0.0)
Requires-Dist: pytest-asyncio (>=0.14.0,<0.15.0)
Requires-Dist: python-configuration (>=0.8.1,<0.9.0)
Requires-Dist: redis-astra (>=2.0.0,<3.0.0)
